aws_costlens/__init__.py
aws_costlens/app_controller.py
aws_costlens/aws_api.py
aws_costlens/cli_commands.py
aws_costlens/common_utils.py
aws_costlens/console_setup.py
aws_costlens/cost_controller.py
aws_costlens/main.py
aws_costlens/models.py
aws_costlens/pdf_renderer.py
aws_costlens/profiles_controller.py
aws_costlens/report_exporter.py
aws_costlens/visuals.py
devops_aws_costlens-1.4.0.dist-info/METADATA
devops_aws_costlens-1.4.0.dist-info/WHEEL
devops_aws_costlens-1.4.0.dist-info/entry_points.txt
devops_aws_costlens-1.4.0.dist-info/licenses/LICENSE
devops_aws_costlens-1.4.0.dist-info/RECORD
