Metadata-Version: 2.4
Name: devops-aws-costlens
Version: 1.4.0
Summary: AWS Cost Intelligence Tool - Terminal-based cost and resource dashboard.
Project-URL: Homepage, https://github.com/Calza36/aws-costlens
Project-URL: Source, https://github.com/Calza36/aws-costlens
Author: Ernesto Calzadilla Martínez
License: MIT
License-File: LICENSE
Keywords: aws,cli,cloud,cost,costlens,dashboard,finops
Classifier: Development Status :: 4 - Beta
Classifier: Environment :: Console
Classifier: Intended Audience :: Developers
Classifier: Intended Audience :: System Administrators
Classifier: License :: OSI Approved :: MIT License
Classifier: Operating System :: OS Independent
Classifier: Programming Language :: Python :: 3
Classifier: Programming Language :: Python :: 3.8
Classifier: Programming Language :: Python :: 3.9
Classifier: Programming Language :: Python :: 3.10
Classifier: Programming Language :: Python :: 3.11
Classifier: Programming Language :: Python :: 3.12
Classifier: Programming Language :: Python :: 3.13
Classifier: Topic :: System :: Monitoring
Classifier: Topic :: Utilities
Requires-Python: >=3.8
Requires-Dist: boto3>=1.37.28
Requires-Dist: pyyaml>=6.0.2
Requires-Dist: reportlab>=3.6.1
Requires-Dist: rich>=14.0.0
Requires-Dist: xlsxwriter>=3.2.0
Provides-Extra: dev
Requires-Dist: black>=23.0.0; extra == 'dev'
Requires-Dist: hatch>=1.9.0; extra == 'dev'
Requires-Dist: isort>=5.12.0; extra == 'dev'
Requires-Dist: mypy>=1.5.1; extra == 'dev'
Requires-Dist: types-boto3; extra == 'dev'
Requires-Dist: types-pyyaml; extra == 'dev'
Requires-Dist: types-reportlab; extra == 'dev'
